pyusatt/__init__.py
pyusatt/data.py
pyusatt-0.0.1.dist-info/LICENSE
pyusatt-0.0.1.dist-info/METADATA
pyusatt-0.0.1.dist-info/WHEEL
pyusatt-0.0.1.dist-info/top_level.txt
pyusatt-0.0.1.dist-info/RECORD
