Metadata-Version: 2.1
Name: pyusatt
Version: 0.0.1
Summary: Python tools for working with the USATT website
Author-email: Shyue Ping Ong <shyuep@gmail.com>
Keywords: usatt,table tennis
Classifier: Programming Language :: Python :: 3
Requires-Python: >=3.10
License-File: LICENSE
Requires-Dist: beautifulsoup4
Requires-Dist: requests
Requires-Dist: lxml
Requires-Dist: pandas
